pvfactors/__init__.py
pvfactors/config.py
pvfactors/engine.py
pvfactors/report.py
pvfactors/run.py
pvfactors/version.py
pvfactors/geometry/__init__.py
pvfactors/geometry/base.py
pvfactors/geometry/plot.py
pvfactors/geometry/pvarray.py
pvfactors/geometry/pvground.py
pvfactors/geometry/pvrow.py
pvfactors/geometry/timeseries.py
pvfactors/geometry/utils.py
pvfactors/irradiance/__init__.py
pvfactors/irradiance/base.py
pvfactors/irradiance/models.py
pvfactors/irradiance/utils.py
pvfactors/viewfactors/__init__.py
pvfactors/viewfactors/aoimethods.py
pvfactors/viewfactors/calculator.py
pvfactors/viewfactors/vfmethods.py
solarfactors-1.6.0.dist-info/LICENSE
solarfactors-1.6.0.dist-info/METADATA
solarfactors-1.6.0.dist-info/WHEEL
solarfactors-1.6.0.dist-info/top_level.txt
solarfactors-1.6.0.dist-info/RECORD
