Metadata-Version: 2.1
Name: solarfactors
Version: 1.6.0
Summary: 2D View Factor Model to calculate the irradiance incident on various surfaces of PV arrays
Author-email: SunPower and pvlib python Developers <pvlib-admin@googlegroups.com>
License: BSD 3-Clause
Project-URL: Bug Tracker, https://github.com/pvlib/solarfactors/issues
Project-URL: Documentation, https://solarfactors.readthedocs.io/
Project-URL: Source Code, https://github.com/pvlib/solarfactors
Classifier: Development Status :: 3 - Alpha
Classifier: License :: OSI Approved :: BSD License
Classifier: Operating System :: OS Independent
Classifier: Intended Audience :: Science/Research
Classifier: Programming Language :: Python
Classifier: Programming Language :: Python :: 3.8
Classifier: Programming Language :: Python :: 3.9
Classifier: Programming Language :: Python :: 3.10
Classifier: Programming Language :: Python :: 3.11
Classifier: Programming Language :: Python :: 3.12
Classifier: Programming Language :: Python :: 3.13
Classifier: Topic :: Scientific/Engineering
Requires-Python: >=3.8
License-File: LICENSE
Requires-Dist: pvlib>=0.9.0
Requires-Dist: shapely>=2.0
Requires-Dist: matplotlib
Requires-Dist: numpy
Requires-Dist: pandas
Provides-Extra: doc
Requires-Dist: sphinx; extra == "doc"
Requires-Dist: sphinx-rtd-theme; extra == "doc"
Requires-Dist: nbsphinx; extra == "doc"
Requires-Dist: sphinxcontrib-github-alt; extra == "doc"
Requires-Dist: ipykernel; extra == "doc"
Provides-Extra: test
Requires-Dist: pytest>=3.2.1; extra == "test"
Requires-Dist: pytest-mock>=1.10.0; extra == "test"
Requires-Dist: mock; extra == "test"
